nion/utils/Binding.py
nion/utils/Color.py
nion/utils/Converter.py
nion/utils/DateTime.py
nion/utils/Event.py
nion/utils/Geometry.py
nion/utils/ListModel.py
nion/utils/Model.py
nion/utils/Observable.py
nion/utils/Platform.py
nion/utils/Process.py
nion/utils/Promise.py
nion/utils/Recorder.py
nion/utils/ReferenceCounting.py
nion/utils/Registry.py
nion/utils/Selection.py
nion/utils/Stream.py
nion/utils/StructuredModel.py
nion/utils/ThreadPool.py
nion/utils/Validator.py
nion/utils/__init__.py
nion/utils/py.typed
nion/utils/test/Binding_test.py
nion/utils/test/Color_test.py
nion/utils/test/Converter_test.py
nion/utils/test/Geometry_test.py
nion/utils/test/ListModel_test.py
nion/utils/test/Model_test.py
nion/utils/test/Observable_test.py
nion/utils/test/Process_test.py
nion/utils/test/Recorder_test.py
nion/utils/test/Registry_test.py
nion/utils/test/Selection_test.py
nion/utils/test/Stream_test.py
nion/utils/test/StructuredModel_test.py
nion/utils/test/__init__.py
nionutils-4.14.1.dist-info/licenses/LICENSE.txt
nionutils-4.14.1.dist-info/METADATA
nionutils-4.14.1.dist-info/WHEEL
nionutils-4.14.1.dist-info/top_level.txt
nionutils-4.14.1.dist-info/RECORD
