Metadata-Version: 2.4
Name: nionutils
Version: 4.14.1
Summary: Nion utility classes.
Home-page: https://github.com/nion-software/nionutils
Author: Nion Software
Author-email: swift@nion.com
License: Apache-2.0
Classifier: Development Status :: 5 - Production/Stable
Classifier: License :: OSI Approved :: Apache Software License
Classifier: Programming Language :: Python :: 3.11
Classifier: Programming Language :: Python :: 3.12
Classifier: Programming Language :: Python :: 3.13
Requires-Python: >=3.11
License-File: LICENSE.txt
Dynamic: license-file
